{
  "$schema": "https://schemas.wp.org/trunk/block.json",
  "apiVersion": 3,
  "name": "brand-standards/brand-guide-section",
  "version": "0.1.0",
  "title": "Brand Guide Section",
  "category": "design",
  "icon": "book-alt",
  "description": "A section for brand guidelines",
  "example": {},
  "supports": {
    "html": false
  },
  "attributes": {
    "sectionTitle": {
      "type": "string",
      "default": ""
    },
    "content": {
      "type": "string",
      "default": ""
    }
  },
  "textdomain": "brand-standards",
  "editorScript": "file:./index.js",
  "editorStyle": "file:./index.css",
  "style": "file:./style-index.css"
}